anacondacode/LICENSE.txt
anacondacode/__init__.py
anacondacode/anacondacode.py
anacondacode-0.0.3.post5.dist-info/METADATA
anacondacode-0.0.3.post5.dist-info/WHEEL
anacondacode-0.0.3.post5.dist-info/top_level.txt
anacondacode-0.0.3.post5.dist-info/RECORD
