Metadata-Version: 2.1
Name: anacondacode
Version: 0.0.3.post5
Summary: anacondacode
Author-email: Ruud van der Ham <rt.van.der.ham@gmail.com>
Project-URL: Homepage, https://github.com/salabim/anacondacode
Project-URL: Repository, https://github.com/salabim/anacondacode
Classifier: Development Status :: 5 - Production/Stable
Classifier: License :: OSI Approved :: MIT License
Classifier: Programming Language :: Python :: 3 :: Only
Requires-Python: >=3.7
